dbt/adapters/avrio/__init__.py
dbt/adapters/avrio/__version__.py
dbt/adapters/avrio/column.py
dbt/adapters/avrio/connections.py
dbt/adapters/avrio/impl.py
dbt/adapters/avrio/relation.py
dbt/adapters/avrio/token_handler.py
dbt/include/avrio/__init__.py
dbt/include/avrio/dbt_project.yml
dbt/include/avrio/sample_profiles.yml
dbt/include/avrio/macros/adapters.sql
dbt/include/avrio/macros/apply_grants.sql
dbt/include/avrio/macros/catalog.sql
dbt/include/avrio/macros/materializations/incremental.sql
dbt/include/avrio/macros/materializations/materialized_view.sql
dbt/include/avrio/macros/materializations/snapshot.sql
dbt/include/avrio/macros/materializations/table.sql
dbt/include/avrio/macros/materializations/view.sql
dbt/include/avrio/macros/materializations/seeds/helpers.sql
dbt/include/avrio/macros/utils/any_value.sql
dbt/include/avrio/macros/utils/array_append.sql
dbt/include/avrio/macros/utils/array_concat.sql
dbt/include/avrio/macros/utils/array_construct.sql
dbt/include/avrio/macros/utils/bool_or.sql
dbt/include/avrio/macros/utils/datatypes.sql
dbt/include/avrio/macros/utils/date_spine.sql
dbt/include/avrio/macros/utils/date_trunc.sql
dbt/include/avrio/macros/utils/dateadd.sql
dbt/include/avrio/macros/utils/datediff.sql
dbt/include/avrio/macros/utils/hash.sql
dbt/include/avrio/macros/utils/listagg.sql
dbt/include/avrio/macros/utils/right.sql
dbt/include/avrio/macros/utils/safe_cast.sql
dbt/include/avrio/macros/utils/split_part.sql
dbt/include/avrio/macros/utils/timestamps.sql
dbt_avrio-20.0.1.dist-info/METADATA
dbt_avrio-20.0.1.dist-info/WHEEL
dbt_avrio-20.0.1.dist-info/top_level.txt
dbt_avrio-20.0.1.dist-info/RECORD
