Metadata-Version: 2.1
Name: dbt-avrio
Version: 20.0.1
Summary: The avrio adapter plugin for dbt (data build tool)
Home-page: https://github.com/avrioproductionsupport/dbt-avrio
Author: Trianz
Author-email: avrioproductionsupport@trianz.com
License: Apache License 2.0
Platform: any
Classifier: Development Status :: 5 - Production/Stable
Classifier: License :: OSI Approved :: Apache Software License
Classifier: Operating System :: Microsoft :: Windows
Classifier: Operating System :: MacOS :: MacOS X
Classifier: Operating System :: POSIX :: Linux
Classifier: Programming Language :: Python :: 3.9
Classifier: Programming Language :: Python :: 3.10
Classifier: Programming Language :: Python :: 3.11
Requires-Python: >=3.8
Requires-Dist: trino~=0.326
Requires-Dist: pyavrio~=20.0.1
Requires-Dist: dbt-core>=1.8
